{"data":[{"book":"Isaya","chapter":"63","verse":"1","text":"Ni nani huyu anayekuja kutoka Edomu,"},{"book":"Isaya","chapter":"63","verse":"2","text":"Kwa nini mavazi yako ni mekundu,"},{"book":"Isaya","chapter":"63","verse":"3","text":"“Nimekanyaga shinikizo la zabibu peke yangu;"},{"book":"Isaya","chapter":"63","verse":"4","text":"Kwa kuwa siku ya kisasi ilikuwa moyoni mwangu,"},{"book":"Isaya","chapter":"63","verse":"5","text":"Nilitazama, lakini hakuwepo yeyote wa kunisaidia,"},{"book":"Isaya","chapter":"63","verse":"6","text":"Nilikanyaga mataifa kwa miguu katika hasira yangu,"},{"book":"Isaya","chapter":"63","verse":"7","text":"Nitasimulia juu ya wema wa Bwana,"},{"book":"Isaya","chapter":"63","verse":"8","text":"Alisema, “Hakika wao ni watu wangu,"},{"book":"Isaya","chapter":"63","verse":"9","text":"Katika taabu zao zote naye alitaabika,"},{"book":"Isaya","chapter":"63","verse":"10","text":"Lakini waliasi,"},{"book":"Isaya","chapter":"63","verse":"11","text":"Ndipo watu wake wakazikumbuka siku zilizopita,"},{"book":"Isaya","chapter":"63","verse":"12","text":"aliyetuma mkono wake uliotukuka wenye nguvu"},{"book":"Isaya","chapter":"63","verse":"13","text":"aliyewaongoza kupitia kwenye vilindi?"},{"book":"Isaya","chapter":"63","verse":"14","text":"kama ngʼombe washukao bondeni kwenye malisho,"},{"book":"Isaya","chapter":"63","verse":"15","text":"Tazama chini kutoka mbinguni ukaone"},{"book":"Isaya","chapter":"63","verse":"16","text":"Lakini wewe ni Baba yetu,"},{"book":"Isaya","chapter":"63","verse":"17","text":"Ee Bwana, kwa nini unatuacha twende mbali na njia zako,"},{"book":"Isaya","chapter":"63","verse":"18","text":"Kwa maana kwa muda mfupi watu wako walimiliki mahali pako patakatifu,"},{"book":"Isaya","chapter":"63","verse":"19","text":"Sisi tumekuwa kama wale ambao hujawatawala kamwe,"}]}