{"data":[{"book":"சங்","chapter":"138","verse":"1","text":"உம்மை என் முழு இருதயத்தோடும் துதிப்பேன்;"},{"book":"சங்","chapter":"138","verse":"2","text":"உமது பரிசுத்த ஆலயத்திற்கு நேராக நான் பணிந்து,"},{"book":"சங்","chapter":"138","verse":"3","text":"நான் கூப்பிட்ட நாளிலே எனக்கு மறுஉத்திரவு அருளினீர்;"},{"book":"சங்","chapter":"138","verse":"4","text":"யெகோவாவே, பூமியின் ராஜாக்களெல்லோரும்"},{"book":"சங்","chapter":"138","verse":"5","text":"யெகோவாவின் மகிமை பெரிதாக இருப்பதினால்,"},{"book":"சங்","chapter":"138","verse":"6","text":"யெகோவா உயர்ந்தவராக இருந்தும்,"},{"book":"சங்","chapter":"138","verse":"7","text":"நான் துன்பத்தின் நடுவில் நடந்தாலும் நீர் என்னை உயிர்ப்பிப்பீர்;"},{"book":"சங்","chapter":"138","verse":"8","text":"யெகோவா எனக்காக யாவையும் செய்து முடிப்பார்;"}]}