{"data":[{"book":"Thaburi","chapter":"30","verse":"1","text":"Wee Jehova-rĩ, nĩngũgũtũũgĩria"},{"book":"Thaburi","chapter":"30","verse":"2","text":"Wee Jehova Ngai wakwa,"},{"book":"Thaburi","chapter":"30","verse":"3","text":"Wee Jehova, wandutire kuuma mbĩrĩra-inĩ;"},{"book":"Thaburi","chapter":"30","verse":"4","text":"Inĩrai Jehova mũmũgooce, inyuĩ andũ ake aamũre;"},{"book":"Thaburi","chapter":"30","verse":"5","text":"nĩgũkorwo marakara make nĩ ma kahinda o kanini,"},{"book":"Thaburi","chapter":"30","verse":"6","text":"Hĩndĩ ĩrĩa ndagaacĩire, ndoigire atĩrĩ,"},{"book":"Thaburi","chapter":"30","verse":"7","text":"Wee Jehova, rĩrĩa wanyonirie ũtugi waku-rĩ,"},{"book":"Thaburi","chapter":"30","verse":"8","text":"Wee Jehova nĩwe ndakaĩire;"},{"book":"Thaburi","chapter":"30","verse":"9","text":"“Mwanangĩko wakwa ũngĩkorwo na uumithio ũrĩkũ,"},{"book":"Thaburi","chapter":"30","verse":"10","text":"Wee Jehova, thikĩrĩria na ũnjiguĩre tha;"},{"book":"Thaburi","chapter":"30","verse":"11","text":"Wagarũrire kĩgirĩko gĩakwa gĩgĩtuĩka rwĩmbo rwa gĩkeno;"},{"book":"Thaburi","chapter":"30","verse":"12","text":"nĩgeetha ngoro yakwa ĩkũinĩre na ndĩgakire."}]}