{"data":[{"book":"Poslovice","chapter":"18","verse":"1","text":"Èovjek samovoljan traži što je njemu milo i miješa se u svašta."},{"book":"Poslovice","chapter":"18","verse":"2","text":"Bezumniku nije mio razum nego da se javlja srce njegovo."},{"book":"Poslovice","chapter":"18","verse":"3","text":"Kad doðe bezbožnik, doðe i rug, i prijekor sa sramotom."},{"book":"Poslovice","chapter":"18","verse":"4","text":"Rijeèi su iz usta èovjeèijih duboka voda, izvor je mudrosti potok koji se ražljeva."},{"book":"Poslovice","chapter":"18","verse":"5","text":"Nije dobro gledati bezbožniku ko je, da se uèini krivo pravomu na sudu."},{"book":"Poslovice","chapter":"18","verse":"6","text":"Usne bezumnikove pristaju u svaðu, i usta njegova dozivlju boj."},{"book":"Poslovice","chapter":"18","verse":"7","text":"Bezumniku su usta njegova pogibao, i usne njegove pruglo duši njegovoj."},{"book":"Poslovice","chapter":"18","verse":"8","text":"Rijeèi su opadaèeve kao izbijenijeh, ali slaze unutra u trbuh."},{"book":"Poslovice","chapter":"18","verse":"9","text":"I ko je nemaran u poslu svom brat je raspikuæi."},{"book":"Poslovice","chapter":"18","verse":"10","text":"Tvrda je kula ime Gospodnje, k njemu æe uteæi pravednik, i biæe u visokom zaklonu."},{"book":"Poslovice","chapter":"18","verse":"11","text":"Bogatstvo je bogatome jak grad i kao visok zid u njegovoj misli."},{"book":"Poslovice","chapter":"18","verse":"12","text":"Pred propast podiže se srce èovjeku, a prije slave ide smjernost."},{"book":"Poslovice","chapter":"18","verse":"13","text":"Ko odgovara prije nego èuje, to mu je ludost i sramota."},{"book":"Poslovice","chapter":"18","verse":"14","text":"Duh èovjeèji snosi bol svoj; a duh oboren ko æe podignuti?"},{"book":"Poslovice","chapter":"18","verse":"15","text":"Srce razumna èovjeka dobavlja znanje, i uho mudrijeh traži znanje."},{"book":"Poslovice","chapter":"18","verse":"16","text":"Dar èovjeku širi mjesto i vodi ga pred vlastelje."},{"book":"Poslovice","chapter":"18","verse":"17","text":"Pravedan se èini ko je prvi u svojoj raspri, ali kad doðe bližnji njegov, ispituje se."},{"book":"Poslovice","chapter":"18","verse":"18","text":"Raspre prekida ždrijeb, i izmeðu silnijeh rasuðuje."},{"book":"Poslovice","chapter":"18","verse":"19","text":"Uvrijeðen je brat kao tvrd grad, i svaða je kao prijevornica na dvoru."},{"book":"Poslovice","chapter":"18","verse":"20","text":"Svakomu se trbuh siti plodom usta njegovijeh, dohotkom od usana svojih siti se."},{"book":"Poslovice","chapter":"18","verse":"21","text":"Smrt je i život u vlasti jeziku, i ko ga miluje, ješæe plod njegov."},{"book":"Poslovice","chapter":"18","verse":"22","text":"Ko je našao ženu, našao je dobro i dobio ljubav od Gospoda."},{"book":"Poslovice","chapter":"18","verse":"23","text":"Siromah govori moleæi, a bogat odgovara oštro."},{"book":"Poslovice","chapter":"18","verse":"24","text":"Ko ima prijatelja, valja da postupa prijateljski, jer ima prijatelja vjernijih od brata."}]}