{"data":[{"book":"Psalms","chapter":"146","verse":"1","text":"Hallelujah! 146:1 Or Hallelu YAH, meaning Praise the LORD; also in verse 10"},{"book":"Psalms","chapter":"146","verse":"2","text":"I will praise the LORD all my life;"},{"book":"Psalms","chapter":"146","verse":"3","text":"Put not your trust in princes,"},{"book":"Psalms","chapter":"146","verse":"4","text":"When his spirit departs, he returns to the ground;"},{"book":"Psalms","chapter":"146","verse":"5","text":"Blessed is he whose help is the God of Jacob,"},{"book":"Psalms","chapter":"146","verse":"6","text":"the Maker of heaven and earth,"},{"book":"Psalms","chapter":"146","verse":"7","text":"He executes justice for the oppressed"},{"book":"Psalms","chapter":"146","verse":"8","text":"the LORD opens the eyes of the blind,"},{"book":"Psalms","chapter":"146","verse":"9","text":"The LORD protects foreigners;"},{"book":"Psalms","chapter":"146","verse":"10","text":"The LORD reigns forever,"}]}