{"data":[{"book":"ಕೀರ್ತ","chapter":"121","verse":"1","text":"ನಾನು ಕಣ್ಣೆತ್ತಿ ಪರ್ವತಗಳ ಕಡೆಗೆ ನೋಡುತ್ತೇನೆ;"},{"book":"ಕೀರ್ತ","chapter":"121","verse":"2","text":"ಭೂಮಿ, ಆಕಾಶಗಳನ್ನು ನಿರ್ಮಿಸಿದ ಯೆಹೋವನಿಂದಲೇ,"},{"book":"ಕೀರ್ತ","chapter":"121","verse":"3","text":"ಆತನು ನಿನ್ನ ಪಾದಗಳನ್ನು ಕದಲಗೊಡಿಸುವುದಿಲ್ಲ;"},{"book":"ಕೀರ್ತ","chapter":"121","verse":"4","text":"ಇಗೋ, ಇಸ್ರಾಯೇಲರನ್ನು ಕಾಯುವಾತನು,"},{"book":"ಕೀರ್ತ","chapter":"121","verse":"5","text":"ನಿನ್ನನ್ನು ಕಾಯುವವನು ಯೆಹೋವನೇ;"},{"book":"ಕೀರ್ತ","chapter":"121","verse":"6","text":"ಹಗಲಿನಲ್ಲಿ ಸೂರ್ಯನೂ, ಇರುಳಿನಲ್ಲಿ ಚಂದ್ರನೂ,"},{"book":"ಕೀರ್ತ","chapter":"121","verse":"7","text":"ಯೆಹೋವನು ನಿನ್ನನ್ನು ಎಲ್ಲಾ ಕೇಡಿನಿಂದ ತಪ್ಪಿಸುವನು;"},{"book":"ಕೀರ್ತ","chapter":"121","verse":"8","text":"ನೀನು ಹೋಗುವಾಗಲೂ, ಬರುವಾಗಲೂ,"}]}