{"data":[{"book":"इब्रानियो","chapter":"3","verse":"1","text":"तानकेरीन एय चोखाला बाय बोणहा, तुमू ज्या हेरगान राज ने हादाड़ेल माय एकठा हेते, तो प्रेरित एने मुखी चाकर्‍यो यीशु पोर जाह आपु कबुल केरतेह, द्यान किरो।"},{"book":"इब्रानियो","chapter":"3","verse":"2","text":"तो तान बोणाव नारान केरता बोरहावालो ईतो, जिहकेरीन मुसा बी बोगवानान आखा गेरा माय ईतो।"},{"book":"इब्रानियो","chapter":"3","verse":"3","text":"एने यीशु मुसाह रेन उलो जादा बोड़ाय ने लायेक सोमजायेल हे। जोलोक काय गेराह बाणावणार गेराह रेन जादा आदार मिलेह।"},{"book":"इब्रानियो","chapter":"3","verse":"4","text":"एकेक गेरान कुण ने कुण बाणावणार रेणे, पुण जो आखो काय बाणायेल तो बोगवान हे।"},{"book":"इब्रानियो","chapter":"3","verse":"5","text":"मुसा ते बोगवानान आखा गेरा माय पावरान गेत बोरहावालो रिनो, ज्यी वातुन वर्णन एण्यो एतो, तान गोवाय देय।"},{"book":"इब्रानियो","chapter":"3","verse":"6","text":"पुण मसी बिटोख एणेन नाते बोगवानान गेरान आदिकारी हे एने तान गेर आपु हेते। केदी आपु दिर पोर एने आपणी आसान मोठवाय पोर सेवली बुखेत वोर मोजबुती माय थोबीन रेहु।"},{"book":"इब्रानियो","chapter":"3","verse":"7","text":"केरीन जीह चोखालो जीव किथे,"},{"book":"इब्रानियो","chapter":"3","verse":"8","text":"ते आपणा मोनाह वातड़ा नाय केरता,"},{"book":"इब्रानियो","chapter":"3","verse":"9","text":"ताहरी तुमरा डायडाया माहु उलखेल एता, एने पारखेन,"},{"book":"इब्रानियो","chapter":"3","verse":"10","text":"ज्यान वोजेसे मी तुलबूखे माणहा हिऱ्यो रागारो रिनो, एने केयो,"},{"book":"इब्रानियो","chapter":"3","verse":"11","text":"तेवी मी रागाम बोरायीन सुगोण खाईल,"},{"book":"इब्रानियो","chapter":"3","verse":"12","text":"एय बाय बोणहा, हास केरीन रिवो काय तुमरे माय ओहलो खाराब एने विण बोरहावालो मोन नाय रेणे जुवे, जो तुमूह जीवताला बोगवाना हिऱ्यो रेन सिटो केर ली जाय।"},{"book":"इब्रानियो","chapter":"3","verse":"13","text":"पुण जाह वोर तो दिह, “जाह आज ने दिह केतेह,” आपणे ओंगाण हे दाड़ीन दिह एका दिहराह उत्साहित केरती रिवो, ओहलो नाय एय काय तुमरे माय रेन कुण बी तान पापान दोका माय आवीन वातड़ो एय जाय।"},{"book":"इब्रानियो","chapter":"3","verse":"14","text":"काहाकाय आपु मसीन गोवांद्या ईयेल हेते, केदी आपु आपणा पेल्ला बोरहा पोर सेवेट वोर मोजबुती माय थोबीन रेहु।"},{"book":"इब्रानियो","chapter":"3","verse":"15","text":"जिहकेरीन चोखाली पुस्तेक माय किथे,"},{"book":"इब्रानियो","chapter":"3","verse":"16","text":"कुण एता ता जा तान आवाज होमेलनेन पासाण बोगवानाह राग लागाड्या? काय ता आखा नाह, जा मुसान द्‍वारे मीस्र देसा माय रेन निकलेल एता?"},{"book":"इब्रानियो","chapter":"3","verse":"17","text":"एने बोगवान चालीह वोरह्या वोर काल्ला माणहा हिऱ्यो रागारो रिनो? कायताच हिऱ्यो नाह जा पाप किरेल एता, एने तान देड़े जेंगला माय पोड़ रियेल एता।"},{"book":"इब्रानियो","chapter":"3","verse":"18","text":"एने बोगवान कुणी हिऱ्यो सुगोण खाईल ईतो, “तुमू मारा हुका माय रिग नाय सिकहो।” काय ताह उलोस नाह जा उकुम नाह मान्या?"},{"book":"इब्रानियो","chapter":"3","verse":"19","text":"आपु देखतेह काय ता विण बोरहान वोजेसे रिग नाह सेकना।"}]}