{"data":[{"book":"Nnwom","chapter":"115","verse":"1","text":"Ɛnyɛ yɛn, Awurade, ɛnyɛ yɛn,"},{"book":"Nnwom","chapter":"115","verse":"2","text":"Adɛn nti na aman no bisa se,"},{"book":"Nnwom","chapter":"115","verse":"3","text":"Yɛn Nyankopɔn wɔ ɔsoro;"},{"book":"Nnwom","chapter":"115","verse":"4","text":"Nanso wɔn ahoni yɛ dwetɛ ne sikakɔkɔɔ a"},{"book":"Nnwom","chapter":"115","verse":"5","text":"Wɔwɔ ano, nanso wontumi nkasa;"},{"book":"Nnwom","chapter":"115","verse":"6","text":"Wɔwɔ aso, nanso wɔnte asɛm;"},{"book":"Nnwom","chapter":"115","verse":"7","text":"Wɔwɔ nsa, nanso wɔnte nka;"},{"book":"Nnwom","chapter":"115","verse":"8","text":"Wɔn a wɔyɛɛ ahoni no bɛyɛ sɛ wɔn ara,"},{"book":"Nnwom","chapter":"115","verse":"9","text":"Mo Israelfo nyinaa, momfa mo ho nto Awurade so,"},{"book":"Nnwom","chapter":"115","verse":"10","text":"Ao Aaronfi, momfa mo ho nto Awurade so,"},{"book":"Nnwom","chapter":"115","verse":"11","text":"Mo a musuro no, momfa mo ho nto Awurade so,"},{"book":"Nnwom","chapter":"115","verse":"12","text":"Awurade kae yɛn na obehyira yɛn:"},{"book":"Nnwom","chapter":"115","verse":"13","text":"Obehyira wɔn a wosuro Awurade,"},{"book":"Nnwom","chapter":"115","verse":"14","text":"Awurade mma wʼase nnɔ,"},{"book":"Nnwom","chapter":"115","verse":"15","text":"Awurade nhyira wo,"},{"book":"Nnwom","chapter":"115","verse":"16","text":"Ɔsorosoro tɔnn yɛ Awurade de,"},{"book":"Nnwom","chapter":"115","verse":"17","text":"Ɛnyɛ awufo na wɔkamfo Awurade"},{"book":"Nnwom","chapter":"115","verse":"18","text":"Yɛn na yɛma Awurade so"}]}